tiledb/segy/__init__.py
tiledb/segy/cli.py
tiledb/segy/convert.py
tiledb/segy/structured.py
tiledb/segy/tdbwrapper.py
tiledb/segy/types.py
tiledb/segy/unstructured.py
tiledb_segy-0.3.1.dist-info/LICENSE
tiledb_segy-0.3.1.dist-info/METADATA
tiledb_segy-0.3.1.dist-info/WHEEL
tiledb_segy-0.3.1.dist-info/entry_points.txt
tiledb_segy-0.3.1.dist-info/top_level.txt
tiledb_segy-0.3.1.dist-info/RECORD
