Metadata-Version: 2.1
Name: tiledb-segy
Version: 0.3.1
Summary: Python library for fast access to seismic data using TileDB
Home-page: https://github.com/TileDB-Inc/TileDB-Segy
Author: George Sakkis
Author-email: george.sakkis@gmail.com
License: MIT
Classifier: Development Status :: 3 - Alpha
Classifier: Environment :: Other Environment
Classifier: Intended Audience :: Developers
Classifier: Intended Audience :: Science/Research
Classifier: License :: OSI Approved :: MIT License
Classifier: Natural Language :: English
Classifier: Programming Language :: Python
Classifier: Programming Language :: Python :: 3
Classifier: Programming Language :: Python :: 3.8
Classifier: Programming Language :: Python :: 3.9
Classifier: Programming Language :: Python :: 3.10
Classifier: Topic :: Scientific/Engineering
Classifier: Topic :: Scientific/Engineering :: Physics
Classifier: Topic :: Software Development :: Libraries
Classifier: Topic :: Utilities
License-File: LICENSE
Requires-Dist: cached-property
Requires-Dist: segyio (>=1.9.6)
Requires-Dist: tiledb (>=0.8.3)
Requires-Dist: urlpath
Requires-Dist: wrapt
